CHANGELOG.txt
LICENSE.txt
MANIFEST.in
README.txt
setup.py
pvishwakarma/__init__.py
pvishwakarma/setup.py
pvishwakarma.egg-info/PKG-INFO
pvishwakarma.egg-info/SOURCES.txt
pvishwakarma.egg-info/dependency_links.txt
pvishwakarma.egg-info/top_level.txt