Metadata-Version: 1.1
Name: pvishwakarma
Version: 0.0.1
Summary: Python Library
Home-page: UNKNOWN
Author: PV
Author-email: pvishwakarma@adaequare.com
License: UNKNOWN
Keywords: library
Platform: UNKNOWN
Classifier: Development Status :: 5 - Production/Stable
Classifier: Intended Audience :: Education
Classifier: Operating System :: Microsoft :: Windows :: Windows 10
Classifier: License :: OSI Approved :: MIT License
Classifier: Programming Language :: Python :: 3
